metapho/__init__.py
metapho/metapho.py
metapho/gtkpho/ImageViewer.py
metapho/gtkpho/__init__.py
metapho/gtkpho/gtkpho.py
metapho/gtkpho/main.py
metapho/scripts/fotogr.py
metapho/scripts/photoshare.py
metapho-1.1.dist-info/COPYING
metapho-1.1.dist-info/METADATA
metapho-1.1.dist-info/WHEEL
metapho-1.1.dist-info/entry_points.txt
metapho-1.1.dist-info/top_level.txt
metapho-1.1.dist-info/RECORD
