Metadata-Version: 2.1
Name: metapho
Version: 1.1
Summary: Image viewer and tagger
Home-page: https://github.com/akkana/metapho
Download-URL: https://github.com/akkana/metapho/tarball/1.0
Author: Akkana Peck
Author-email: akkana@shallowsky.com
License: GPLv2+
Keywords: image,viewer,tagger
Classifier: Programming Language :: Python :: 2
Classifier: Programming Language :: Python :: 3
Classifier: License :: OSI Approved :: GNU General Public License v2 or later (GPLv2+)
Classifier: Intended Audience :: End Users/Desktop
Classifier: Topic :: Multimedia :: Graphics
Classifier: Topic :: Multimedia :: Graphics :: Viewers
Classifier: Topic :: Utilities
License-File: COPYING
Requires-Dist: PyGObject
Requires-Dist: pycairo
